inferelator_prior/__init__.py
inferelator_prior/expression_data_from_srr.py
inferelator_prior/link_atac_bed_to_genes.py
inferelator_prior/make_regulator_bed.py
inferelator_prior/mkref.py
inferelator_prior/motif_information.py
inferelator_prior/network_from_motifs.py
inferelator_prior/network_from_motifs_fasta.py
inferelator_prior/pwm_to_meme.py
inferelator_prior/motifs/__init__.py
inferelator_prior/motifs/_motif.py
inferelator_prior/motifs/fimo.py
inferelator_prior/motifs/homer.py
inferelator_prior/motifs/homer_motif.py
inferelator_prior/motifs/meme.py
inferelator_prior/motifs/motif_loader.py
inferelator_prior/motifs/motif_scan.py
inferelator_prior/motifs/pwm.py
inferelator_prior/motifs/transfac.py
inferelator_prior/processor/__init__.py
inferelator_prior/processor/bedtools.py
inferelator_prior/processor/gtf.py
inferelator_prior/processor/htseq_count.py
inferelator_prior/processor/kallisto.py
inferelator_prior/processor/matrix.py
inferelator_prior/processor/prior.py
inferelator_prior/processor/samtools.py
inferelator_prior/processor/species_constants.py
inferelator_prior/processor/srr.py
inferelator_prior/processor/star.py
inferelator_prior/processor/utils.py
inferelator_prior/tests/__init__.py
inferelator_prior/tests/test_motif.py
inferelator_prior/tests/test_motif_scan.py
inferelator_prior/tests/test_network_maker.py
inferelator_prior/tests/test_prior.py
inferelator_prior/tests/test_srr.py
inferelator_prior/tests/test_star.py
inferelator_prior/tests/test_utils.py
inferelator_prior/tests/test_velocity.py
inferelator_prior/velocity/__init__.py
inferelator_prior/velocity/calc.py
inferelator_prior/velocity/decay.py
inferelator_prior/velocity/times.py
inferelator_prior-0.3.8.dist-info/LICENSE
inferelator_prior-0.3.8.dist-info/METADATA
inferelator_prior-0.3.8.dist-info/WHEEL
inferelator_prior-0.3.8.dist-info/top_level.txt
inferelator_prior-0.3.8.dist-info/RECORD
