Metadata-Version: 2.1
Name: inferelator-prior
Version: 0.3.8
Summary: Inferelator-Prior Network Generation Tool
Home-page: https://github.com/flatironinstitute/inferelator-prior
Author: Chris Jackson
Author-email: cj59@nyu.edu
Maintainer: Chris Jackson
Maintainer-email: cj59@nyu.edu
License: UNKNOWN
Platform: UNKNOWN
License-File: LICENSE
Requires-Dist: numpy
Requires-Dist: pandas (>=1.0)
Requires-Dist: HTSeq
Requires-Dist: pybedtools
Requires-Dist: scipy
Requires-Dist: pathos
Requires-Dist: sklearn
Requires-Dist: tqdm
